{
  "generatedAt": "2026-02-07",
  "workspace": "D:/dev/kord-aios",
  "checks": {
    "cloneFromOmoc": "ok",
    "npmInstall": "ok",
    "typecheck": "ok",
    "tests": "blocked-bun-missing",
    "aiosLayerSync": "ok",
    "kordAliasInRunner": "ok"
  },
  "artifacts": {
    "migrationPlan": "docs/migration/kord-aios-migration-plan.md",
    "taskBoard": "docs/migration/kord-aios-task-board.md",
    "layerRoot": "layer/aios",
    "syncScript": "script/sync-aios-layer.mjs"
  },
  "next": "Implement installer command overlay: kord-aios init and AIOS layer project bootstrap."
}